formatron/__init__.py
formatron/config.py
formatron/extractor.py
formatron/formatter.py
formatron/formats/__init__.py
formatron/formats/json.py
formatron/formats/regex.py
formatron/formats/utils.py
formatron/integrations/RWKV.py
formatron/integrations/__init__.py
formatron/integrations/exllamav2.py
formatron/integrations/transformers.py
formatron/integrations/utils.py
formatron/integrations/vllm.py
formatron/schemas/__init__.py
formatron/schemas/dict_inference.py
formatron/schemas/json_schema.py
formatron/schemas/pydantic.py
formatron/schemas/schema.py
formatron-0.5.0.dist-info/licenses/LICENSE
formatron-0.5.0.dist-info/METADATA
formatron-0.5.0.dist-info/WHEEL
formatron-0.5.0.dist-info/top_level.txt
formatron-0.5.0.dist-info/RECORD
