Metadata-Version: 2.4
Name: formatron
Version: 0.5.0
Summary: Formatron empowers everyone to control the output format of language models with minimal overhead.
Author-email: Xintong Sun <xs28@rice.edu>
License: MIT License
Project-URL: Repository, https://github.com/Dan-wanna-M/formatron
Keywords: deep learning,language model,guided generation,structured generation,constrained decoding
Classifier: Development Status :: 4 - Beta
Classifier: Intended Audience :: Developers
Classifier: Intended Audience :: Science/Research
Classifier: Operating System :: OS Independent
Classifier: Topic :: Scientific/Engineering :: Artificial Intelligence
Classifier: Topic :: Text Processing
Classifier: Programming Language :: Python :: Implementation :: CPython
Requires-Python: >=3.10
License-File: LICENSE
Requires-Dist: pydantic<3,>=2
Requires-Dist: kbnf<0.5.0,>=0.4.0
Requires-Dist: general-sam<2,>=1
Requires-Dist: jsonschema<5,>=4
Requires-Dist: frozendict<3,>=2
Provides-Extra: rwkv
Requires-Dist: rwkv<0.9.0,>=0.7.4; extra == "rwkv"
Provides-Extra: transformers
Requires-Dist: transformers<5,>=4; extra == "transformers"
Provides-Extra: exllamav2
Requires-Dist: exllamav2<0.4.0,>=0.0.17; extra == "exllamav2"
Provides-Extra: vllm
Requires-Dist: vllm<0.9.0,>=0.2.2; extra == "vllm"
Dynamic: license-file
